[
  {
    "content": null,
    "href": "/bbs/StupidClown/M.1498545821.A.9EB.html",
    "push_count": 2000,
    "title": "[大哭] 之後我都不知道該怎麼面對男友爸了"
  },
  {
    "content": null,
    "href": "/bbs/StupidClown/M.1498563348.A.4C5.html",
    "push_count": 2000,
    "title": "[大哭] 還沒上班就要失業了"
  },
  {
    "content": null,
    "href": "/bbs/StupidClown/M.1498567077.A.392.html",
    "push_count": 66,
    "title": "[聽錯] 小鳥"
  },
  {
    "content": null,
    "href": "/bbs/StupidClown/M.1498576978.A.EEE.html",
    "push_count": 2000,
    "title": "[無言] 第一次被嗆到無言"
  },
  {
    "content": null,
    "href": "/bbs/StupidClown/M.1498579958.A.A97.html",
    "push_count": 97,
    "title": "[無言]品牌迷思"
  },
  {
    "content": null,
    "href": "/bbs/StupidClown/M.1498471551.A.441.html",
    "push_count": 51,
    "title": "[眼殘] 停車前眼睛要睜亮點(￣ー￣)"
  },
  {
    "content": null,
    "href": "/bbs/StupidClown/M.1498480963.A.F74.html",
    "push_count": 2000,
    "title": "[眼殘] 開信箱被侯昌明嚇死"
  },
  {
    "content": null,
    "href": "/bbs/StupidClown/M.1498404654.A.A62.html",
    "push_count": 2000,
    "title": "[大哭] 吃叔叔"
  },
  {
    "content": null,
    "href": "/bbs/StupidClown/M.1498428121.A.495.html",
    "push_count": 95,
    "title": "[無言] 好吃的晚餐"
  },
  {
    "content": null,
    "href": "/bbs/StupidClown/M.1498299573.A.754.html",
    "push_count": 2000,
    "title": "[恍神] 你要不要上床"
  },
  {
    "content": null,
    "href": "/bbs/StupidClown/M.1498308198.A.C3D.html",
    "push_count": 71,
    "title": "[大哭] 不會講就不要丟臉嘛(′Д⊂ヽ"
  },
  {
    "content": null,
    "href": "/bbs/StupidClown/M.1498361376.A.B7F.html",
    "push_count": 2000,
    "title": "[眼殘] 臉盲重症患者"
  },
  {
    "content": null,
    "href": "/bbs/StupidClown/M.1498378779.A.46B.html",
    "push_count": 67,
    "title": "[大哭] 難忘的體檢"
  },
  {
    "content": null,
    "href": "/bbs/StupidClown/M.1498230390.A.427.html",
    "push_count": 2000,
    "title": "[無言] 又浪費時間了"
  },
  {
    "content": null,
    "href": "/bbs/StupidClown/M.1498236121.A.F70.html",
    "push_count": 2000,
    "title": "[無言] 姊姊的女兒"
  },
  {
    "content": null,
    "href": "/bbs/StupidClown/M.1498124424.A.293.html",
    "push_count": 97,
    "title": "[大哭] 妳殺人了啊？！！(有圖慎滑"
  },
  {
    "content": null,
    "href": "/bbs/StupidClown/M.1498150055.A.D7B.html",
    "push_count": 74,
    "title": "[無言] 瓶中信"
  },
  {
    "content": null,
    "href": "/bbs/StupidClown/M.1498206552.A.0B1.html",
    "push_count": 95,
    "title": "[無言] 可愛的主管"
  },
  {
    "content": null,
    "href": "/bbs/StupidClown/M.1497972316.A.316.html",
    "push_count": 2000,
    "title": "[無言] 戴面具的狗"
  },
  {
    "content": null,
    "href": "/bbs/StupidClown/M.1498068079.A.A06.html",
    "push_count": 2000,
    "title": "[聽錯] 噫，我備上了！"
  },
  {
    "content": null,
    "href": "/bbs/StupidClown/M.1497928284.A.E81.html",
    "push_count": 2000,
    "title": "[無言] 教育局我又來了"
  },
  {
    "content": null,
    "href": "/bbs/StupidClown/M.1497953295.A.20E.html",
    "push_count": 56,
    "title": "[大哭] 哭…跑出來了…有點噁慎入…"
  },
  {
    "content": null,
    "href": "/bbs/StupidClown/M.1497971411.A.E5F.html",
    "push_count": 2000,
    "title": "[無言] 對...是本人取貨......"
  },
  {
    "content": null,
    "href": "/bbs/StupidClown/M.1497850107.A.D5E.html",
    "push_count": 66,
    "title": "[無言] 白玉軒？"
  },
  {
    "content": null,
    "href": "/bbs/StupidClown/M.1497863945.A.44B.html",
    "push_count": 2000,
    "title": "[眼殘] 白貓"
  },
  {
    "content": null,
    "href": "/bbs/StupidClown/M.1497872310.A.CE5.html",
    "push_count": 2000,
    "title": "[眼殘] 這到底是什麼動物啊"
  }
]